firefox_forensics-1.0.1b0.dist-info/licenses/LICENSE
src/__init__.py
src/argument_handler.py
src/common.py
src/firefox_data.py
src/info.py
src/main.py
firefox_forensics-1.0.1b0.dist-info/METADATA
firefox_forensics-1.0.1b0.dist-info/WHEEL
firefox_forensics-1.0.1b0.dist-info/entry_points.txt
firefox_forensics-1.0.1b0.dist-info/top_level.txt
firefox_forensics-1.0.1b0.dist-info/RECORD
