Metadata-Version: 2.4
Name: firefox-forensics
Version: 1.0.1b0
Summary: Read data from Firefox browser and extract useful information.
Home-page: https://github.com/niftycode/firefox-forensics
Author: Bodo Schönfeld
Author-email: bodo.schoenfeld@niftycode.de
License: MIT
Classifier: Intended Audience :: Developers
Classifier: Development Status :: 4 - Beta
Classifier: License :: OSI Approved :: MIT License
Classifier: Operating System :: MacOS
Classifier: Programming Language :: Python :: 3
Classifier: Programming Language :: Python :: 3.13
Classifier: Programming Language :: Python :: 3.14
Classifier: Programming Language :: Python :: Implementation :: CPython
License-File: LICENSE
Requires-Dist: setuptools>=70
Dynamic: license-file
